{
  "source": "Bills API",
  "fetched_at": "20260613T021002Z",
  "total_bills": 3513,
  "total_details": 3513,
  "unique_members": [
    "Alastair Scott",
    "Allan Peachey",
    "Anahila Kanongata'a",
    "Anahila Kanongata'a-Suisuiki",
    "Andrew Bayly",
    "Andy Foster",
    "Angie Warren-Clark",
    "Annabel Young",
    "Arena Williams",
    "Barbara Kuriger",
    "Barbara Stewart",
    "Belinda Vernon",
    "Bob Simcock",
    "Brendon Burns",
    "Brett Hudson",
    "Brian Neeson",
    "Brooke van Velden",
    "Cameron Luxton",
    "Camilla Belich",
    "Carl Bates",
    "Carol Beaumont",
    "Catherine Delahunty",
    "Catherine Wedd",
    "Chlöe Swarbrick",
    "Chris Auchinvole",
    "Chris Baillie",
    "Chris Bishop",
    "Chris Penk",
    "Clayton Mitchell",
    "Craig McNair",
    "Cushla Tangaere-Manuel",
    "Damien Smith",
    "Dan Bidois",
    "Dana Kirkpatrick",
    "Darien Fenton",
    "Darroch Ball",
    "David Clendon",
    "David Garrett",
    "David Seymour",
    "David Shearer",
    "Debbie Ngarewa-Packer",
    "Denis O'Rourke",
    "Denise Lee",
    "Dianne Yates",
    "Donna Awatere Huata",
    "Dr Cam Calder",
    "Dr Carlos Cheung",
    "Dr Hamish Campbell",
    "Dr Jackie Blue",
    "Dr James McDowall",
    "Dr Jian Yang",
    "Dr Kennedy Graham",
    "Dr Muriel Newman",
    "Dr Parmjeet Parmar",
    "Dr Paul Hutchison",
    "Dr Russel Norman",
    "Dr Shane Reti",
    "Dr The Rt Hon Lockwood Smith",
    "Dr Tracey McLellan",
    "Dr Vanessa Weenink",
    "Eric Roy",
    "Erica Stanford",
    "Fletcher Tabuteau",
    "Gareth Hughes",
    "Geoff Braybrooke",
    "Georgina Beyer",
    "Gerrard Eckhoff",
    "Glen Bennett",
    "Golriz Ghahraman",
    "Gordon Copeland",
    "Graham Kelly",
    "Grant Gillon",
    "Greg Fleming",
    "Greg O'Connor",
    "H V Ross Robertson",
    "Hamish Walker",
    "Harete Hipango",
    "Helen Duncan",
    "Helen White",
    "Holly Walker",
    "Hon Alfred Ngaro",
    "Hon Amy Adams",
    "Hon Andrew Bayly",
    "Hon Andrew Hoggard",
    "Hon Andrew Little",
    "Hon Anne Tolley",
    "Hon Annette King",
    "Hon Aupito William Sio",
    "Hon Barbara Edmonds",
    "Hon Brian Donnelly",
    "Hon Brooke van Velden",
    "Hon Cameron Brewer",
    "Hon Carmel Sepuloni",
    "Hon Casey Costello",
    "Hon Chester Borrows",
    "Hon Chris Bishop",
    "Hon Chris Carter",
    "Hon Chris Penk",
    "Hon Chris Tremain",
    "Hon Christopher Finlayson",
    "Hon Clare Curran",
    "Hon Clayton Cosgrove",
    "Hon Clem Simich",
    "Hon Craig Foss",
    "Hon Damien O'Connor",
    "Hon Darren Hughes",
    "Hon David Bennett",
    "Hon David Benson-Pope",
    "Hon David Cunliffe",
    "Hon David Parker",
    "Hon David Seymour",
    "Hon Denis Marshall",
    "Hon Derek Quigley",
    "Hon Doug Kidd",
    "Hon Dr Ayesha Verrall",
    "Hon Dr David Clark",
    "Hon Dr Deborah Russell",
    "Hon Dr Duncan Webb",
    "Hon Dr Jonathan Coleman",
    "Hon Dr Megan Woods",
    "Hon Dr Michael Cullen",
    "Hon Dr Nick Smith",
    "Hon Dr Pita Sharples",
    "Hon Dr Shane Reti",
    "Hon Dr Wayne Mapp",
    "Hon Erica Stanford",
    "Hon Eugenie Sage",
    "Hon George Hawkins",
    "Hon Georgina te Heuheu",
    "Hon Gerry Brownlee",
    "Hon Ginny Andersen",
    "Hon Grant Robertson",
    "Hon Harry Duynhoven",
    "Hon Heather Roy",
    "Hon Hekia Parata",
    "Hon Iain Lees-Galloway",
    "Hon Jack Elder",
    "Hon Jacqui Dean",
    "Hon James Meager",
    "Hon James Shaw",
    "Hon Jan Tinetti",
    "Hon Jenny Salesa",
    "Hon Jim Anderton",
    "Hon Jim Sutton",
    "Hon Jo Goodhew",
    "Hon Jo Luxton",
    "Hon John Banks",
    "Hon John Boscawen",
    "Hon John Carter",
    "Hon John Luxton",
    "Hon Judith Collins",
    "Hon Judith Tizard",
    "Hon Julie Anne Genter",
    "Hon Karen Chhour",
    "Hon Kate Wilkinson",
    "Hon Katherine O'Regan",
    "Hon Kelvin Davis",
    "Hon Ken Shirley",
    "Hon Kieran McAnulty",
    "Hon Kiritapu Allan",
    "Hon Kris Faafoi",
    "Hon Laila Harre",
    "Hon Lianne Dalziel",
    "Hon Louise Upston",
    "Hon Luamanuvao Winnie Laban",
    "Hon Maggie Barry",
    "Hon Marama Davidson",
    "Hon Margaret Wilson",
    "Hon Marian Hobbs",
    "Hon Marie Hasler",
    "Hon Mark Burton",
    "Hon Mark Mitchell",
    "Hon Maryan Street",
    "Hon Matt Doocey",
    "Hon Matt Robson",
    "Hon Maurice Williamson",
    "Hon Max Bradford",
    "Hon Meka Whaitiri",
    "Hon Michael Wood",
    "Hon Michael Woodhouse",
    "Hon Mike Butterick",
    "Hon Mita Ririnui",
    "Hon Murray McCully",
    "Hon Nanaia Mahuta",
    "Hon Nathan Guy",
    "Hon Neil Kirton",
    "Hon Nicky Wagner",
    "Hon Nicola Grigg",
    "Hon Nicola Willis",
    "Hon Nicole McKee",
    "Hon Nikki Kaye",
    "Hon Parekura Horomia",
    "Hon Paul Goldsmith",
    "Hon Paul Swain",
    "Hon Paula Bennett",
    "Hon Peeni Henare",
    "Hon Penny Simmonds",
    "Hon Peseta Sam Lotu-Iiga",
    "Hon Pete Hodgson",
    "Hon Peter Dunne",
    "Hon Peter McCardle",
    "Hon Phil Goff",
    "Hon Phil Heatley",
    "Hon Phil Twyford",
    "Hon Poto Williams",
    "Hon Priyanca Radhakrishnan",
    "Hon Richard Prebble",
    "Hon Rick Barker",
    "Hon Rino Tirikatene",
    "Hon Rodney Hide",
    "Hon Roger Sowry",
    "Hon Ron Mark",
    "Hon Ruth Dyson",
    "Hon Sandra Lee",
    "Hon Scott Simpson",
    "Hon Shane Jones",
    "Hon Simeon Brown",
    "Hon Simon Bridges",
    "Hon Simon Power",
    "Hon Simon Watts",
    "Hon Sir Roger Douglas",
    "Hon Steve Chadwick",
    "Hon Steve Maharey",
    "Hon Steven Joyce",
    "Hon Stuart Nash",
    "Hon Tama Potaka",
    "Hon Tariana Turia",
    "Hon Tau Henare",
    "Hon Te Ururoa Flavell",
    "Hon Tim Groser",
    "Hon Todd McClay",
    "Hon Tony Ryall",
    "Hon Tracey Martin",
    "Hon Tuariki John Delamere",
    "Hon Vui Mark Gosche",
    "Hon Willie Jackson",
    "Hon Willow-Jean Prime",
    "Hūhana Lyndon",
    "Ian Ewen-Street",
    "Ian McKelvie",
    "Ingrid Leary",
    "Jami-Lee Ross",
    "Jamie Strange",
    "Jan Logie",
    "Janet Mackey",
    "Jeanette Fitzsimons",
    "Jenny Marcroft",
    "Jill Pettis",
    "Joanne Hayes",
    "John Tamihere",
    "Jonathan Young",
    "Joseph Mooney",
    "Joy Quigley",
    "Judy Keall",
    "Judy Turner",
    "Kahurangi Carter",
    "Kanwaljit Singh Bakshi",
    "Karen Chhour",
    "Katie Nimon",
    "Keith Locke",
    "Kiritapu Allan",
    "Lan Pham",
    "Larry Sutherland",
    "Laura McClure",
    "Le'aufa'amulia Asenati Lole-Taylor",
    "Lemauga Lydia Sosene",
    "Liz Gordon",
    "Louisa Wall",
    "Lynne Pillay",
    "Marama Fox",
    "Marc Alexander",
    "Marja Lubeck",
    "Mark Cameron",
    "Mark Patterson",
    "Mark Peck",
    "Martin Gallagher",
    "Matt Doocey",
    "Matt King",
    "Maureen Pugh",
    "Maurice Patrick McTigue",
    "Melissa Lee",
    "Metiria Turei",
    "Mike Butterick",
    "Mike Sabin",
    "Moana Lynore Mackey",
    "Mojo Mathers",
    "Mr Frank Grover",
    "Nicola Willis",
    "Nicole McKee",
    "Nuk Korako",
    "Nándor Tánczos",
    "Owen Jennings",
    "Pam Corkery",
    "Pansy Wong",
    "Patricia Schnauer",
    "Paul Foster-Bell",
    "Paul Quinn",
    "Paulo Garcia",
    "Peter Brown",
    "Phillida Bunkle",
    "Pita Paraone",
    "R Doug Woolerton",
    "Rachel Boyack",
    "Rahui Katene",
    "Rawiri Waititi",
    "Ricardo Menéndez March",
    "Rima Nakhle",
    "Rod Donald",
    "Rt Hon Adrian Rurawhe",
    "Rt Hon Bill Birch",
    "Rt Hon Bill English",
    "Rt Hon Chris Hipkins",
    "Rt Hon DAM Graham",
    "Rt Hon David Carter",
    "Rt Hon Don McKinnon",
    "Rt Hon Gerry Brownlee",
    "Rt Hon Helen Clark",
    "Rt Hon Jacinda Ardern",
    "Rt Hon Jenny Shipley",
    "Rt Hon John Key",
    "Rt Hon Jonathan Hunt",
    "Rt Hon Mike Moore",
    "Rt Hon Simon Upton",
    "Rt Hon Trevor Mallard",
    "Rt Hon Winston Peters",
    "Rt Hon Wyatt Creech",
    "Sandra Goudie",
    "Sarah Dowie",
    "Shanan Halbert",
    "Shane Ardern",
    "Simeon Brown",
    "Simon O'Connor",
    "Simon Watts",
    "Steph Lewis",
    "Stephen Franks",
    "Stuart Smith",
    "Sue Bradford",
    "Sue Kedgley",
    "Sue Moroney",
    "Taito Phillip Field",
    "Tangi Utikere",
    "Teanau Tuiono",
    "Terisa Ngobi",
    "Tim Barnett",
    "Tim Costley",
    "Tim van de Molen",
    "Todd Muller",
    "Todd Stephenson",
    "Tom Rutherford",
    "Tony Steel",
    "Tāmati Coffey"
  ],
  "member_count": 351
}
